allye_data_connector/__init__.py
allye_data_connector/connector.py
allye_data_connector/lock.py
allye_data_connector/manifest.py
allye_data_connector/storage.py
allye_data_connector/util.py
allye_data_connector-0.1.2.dist-info/licenses/LICENSE
allye_data_connector-0.1.2.dist-info/METADATA
allye_data_connector-0.1.2.dist-info/WHEEL
allye_data_connector-0.1.2.dist-info/top_level.txt
allye_data_connector-0.1.2.dist-info/RECORD
