Metadata-Version: 2.4
Name: allye_data_connector
Version: 0.1.2
Summary: Local DataFrame connector between Python and Allye widgets via manifest.jsonl + shared storage.
Author: Allye
License-Expression: Apache-2.0
Project-URL: Homepage, https://github.com/LichtLab/allye_data_connector
Project-URL: Repository, https://github.com/LichtLab/allye_data_connector/tree/main
Project-URL: Issues, https://github.com/LichtLab/allye_data_connector/issues
Classifier: Programming Language :: Python :: 3
Classifier: Programming Language :: Python :: 3 :: Only
Classifier: Programming Language :: Python :: 3.9
Classifier: Programming Language :: Python :: 3.10
Classifier: Programming Language :: Python :: 3.11
Classifier: Programming Language :: Python :: 3.12
Requires-Python: >=3.9
License-File: LICENSE
Requires-Dist: pandas>=2.0
Requires-Dist: pyarrow>=12.0
Dynamic: license-file
